vimoku.py
vimoku-1.1.2.dist-info/METADATA
vimoku-1.1.2.dist-info/WHEEL
vimoku-1.1.2.dist-info/top_level.txt
vimoku-1.1.2.dist-info/RECORD
