Metadata-Version: 2.1
Name: vimoku
Version: 1.1.2
Summary: Edit pages of a dokuwiki instance with your favorite editor
Home-page: https://github.com/aluriak/vimoku
Author: Lucas Bourneuf
Author-email: lucas.bourneuf@laposte.net
License: GPLv3
Keywords: wiki editor
Platform: UNKNOWN
Classifier: License :: OSI Approved :: GNU General Public License v3 (GPLv3)
Classifier: Development Status :: 4 - Beta
Classifier: Programming Language :: Python :: 3
Classifier: Programming Language :: Python :: 3.6
Classifier: Programming Language :: Python :: 3.7
Requires-Dist: dokuwikixmlrpc (==2020.5.23)
